MANIFEST.in
README.md
setup.py
sm_lib/__init__.py
sm_lib/authors.jpg
sm_lib/core.py
sm_lib.egg-info/PKG-INFO
sm_lib.egg-info/SOURCES.txt
sm_lib.egg-info/dependency_links.txt
sm_lib.egg-info/entry_points.txt
sm_lib.egg-info/top_level.txt